{"data":{"sitePage":{"context":{"locale":"en","page":{"artist":{"key":"bernhard-heiliger","name":"Bernhard","preposition":"","lastname":"Heiliger","works":[{"key":"ohne-titel"}]},"work":{"key":"ohne-titel","date":"1963","images":["ohne-titel.jpeg"],"title":"Ohne Titel","description":["Mischtechnik auf Papier","99 x 68 cm","signiert und datiert unten links: B. Heiliger 63"],"width":"99 cm","depth":null,"height":"68 cm","medium":"Mischtechnik","surface":"Papier"},"previous":null,"next":null}}}},"pageContext":{"languages":{"de":"Deutsch","en":"English"},"locale":"en","routed":true,"originalPath":"/bernhard-heiliger/ohne-titel","page":{"artist":{"key":"bernhard-heiliger","name":"Bernhard","preposition":"","lastname":"Heiliger","available":true,"birthdate":"1915","deathdate":"1995","description":[],"works":[{"key":"ohne-titel","title":"Ohne Titel","date":"1963","description":["Mischtechnik auf Papier","99 x 68 cm","signiert und datiert unten links: B. Heiliger 63"],"width":"99 cm","height":"68 cm","medium":"Mischtechnik","surface":"Papier","images":["ohne-titel.jpeg"]}]},"next":null,"previous":null,"work":{"key":"ohne-titel","title":"Ohne Titel","date":"1963","description":["Mischtechnik auf Papier","99 x 68 cm","signiert und datiert unten links: B. Heiliger 63"],"width":"99 cm","height":"68 cm","medium":"Mischtechnik","surface":"Papier","images":["ohne-titel.jpeg"]}}}}